{"noiseKey":{"private":{"type":"Buffer","data":"MLysgj6XpP/eTIHC1NQlCbFNQBxWaaYZtxnef2OkNlY="},"public":{"type":"Buffer","data":"ebBzXx9vWTWE804/ZeZjyJtm1Ls5EBIKffpmEavXNHE="}},"pairingEphemeralKeyPair":{"private":{"type":"Buffer","data":"kBVn/rEA2p61IxSFGGwE4csDBIa8U/vXxwT3VxtuGHc="},"public":{"type":"Buffer","data":"dJqkNEtfji1+EYu2d2qHgnIBlXDcHgxIOtXFCZzegUc="}},"signedIdentityKey":{"private":{"type":"Buffer","data":"OB4jBc5VvWinNoDej/JzhBouQQa2pAb1oMvkkgGYU30="},"public":{"type":"Buffer","data":"5t6wzTLNFUWSQAsW6x1v9mkxWfbKbjNG3v5GVh4+Ck4="}},"signedPreKey":{"keyPair":{"private":{"type":"Buffer","data":"0MNF2V98yQZT15Kx2iX9UlFPE50OANkq/32SXPvYZlU="},"public":{"type":"Buffer","data":"pnu46Z4CdXExNakyfM1JYWY9ztwb+jL3OT6XvyPWdn8="}},"signature":{"type":"Buffer","data":"5rxTm5gAixz11CoN0IYtIEAHv/ux+3Y9IHDprDfWiwbz/AGMQ8S3KSN0RAk0SKK31Jsa8ZU7jdaENhq8zkOdiA=="},"keyId":1},"registrationId":186,"advSecretKey":"YcCAZqJnDOyO8zrwO1JBs+wH2rWUa1EqOskngeQ+8eQ=","processedHistoryMessages":[{"key":{"remoteJid":"553892093116@s.whatsapp.net","fromMe":false,"id":"ACA3F67A26FBD38D37C39B1EDB958204","participant":"","addressingMode":"pn"},"messageTimestamp":1768869346},{"key":{"remoteJid":"553892093116@s.whatsapp.net","fromMe":false,"id":"AC84FC144D96D9C23357A71D5CD379D9","participant":"","addressingMode":"pn"},"messageTimestamp":1768869346},{"key":{"remoteJid":"553892093116@s.whatsapp.net","fromMe":false,"id":"AC0B73C7BFAFDD63642E5D7DF44C721E","participant":"","addressingMode":"pn"},"messageTimestamp":1768869347},{"key":{"remoteJid":"553892093116@s.whatsapp.net","fromMe":false,"id":"AC73847995F12243937358AC7D0139F0","participant":"","addressingMode":"pn"},"messageTimestamp":1768869348},{"key":{"remoteJid":"553892093116@s.whatsapp.net","fromMe":false,"id":"AC4436B1699BD87F934158F86EFAB38C","participant":"","addressingMode":"pn"},"messageTimestamp":1768869368},{"key":{"remoteJid":"553892093116@s.whatsapp.net","fromMe":false,"id":"ACB924F41AB14949C69979CB3AC947F6","participant":"","addressingMode":"pn"},"messageTimestamp":1768869383},{"key":{"remoteJid":"553892093116@s.whatsapp.net","fromMe":false,"id":"ACDBED18EFC5086CC02DA39BE09AC0E7","participant":"","addressingMode":"pn"},"messageTimestamp":1768869399},{"key":{"remoteJid":"553892093116@s.whatsapp.net","fromMe":false,"id":"ACA0D79BA97A7FA4BACBD84D6507D594","participant":"","addressingMode":"pn"},"messageTimestamp":1768903873},{"key":{"remoteJid":"553892093116@s.whatsapp.net","fromMe":false,"id":"AC28C59610284471BDEEAE531545E0B1","participant":"","addressingMode":"pn"},"messageTimestamp":1768903904},{"key":{"remoteJid":"553892093116@s.whatsapp.net","fromMe":false,"id":"AC13B77B0B4670A10603F68F4F3D2B6E","participant":"","addressingMode":"pn"},"messageTimestamp":1768903929},{"key":{"remoteJid":"553892093116@s.whatsapp.net","fromMe":false,"id":"AC3FDE5D23226EA3B2C7BF2FDDAA1ACB","participant":"","addressingMode":"pn"},"messageTimestamp":1768903948},{"key":{"remoteJid":"553892093116@s.whatsapp.net","fromMe":false,"id":"ACE033D7AEF5BA390DCE274EB39D9466","participant":"","addressingMode":"pn"},"messageTimestamp":1768903952},{"key":{"remoteJid":"553892093116@s.whatsapp.net","fromMe":false,"id":"ACADBC0326B46F63ADEF5AA2CB4EF171","participant":"","addressingMode":"pn"},"messageTimestamp":1768903970},{"key":{"remoteJid":"553892093116@s.whatsapp.net","fromMe":false,"id":"ACB5EF6CC24E71C996FB8D925FB10533","participant":"","addressingMode":"pn"},"messageTimestamp":1768903987},{"key":{"remoteJid":"553892093116@s.whatsapp.net","fromMe":false,"id":"AC9A43830B5A7F19FE203EF53DD64AD7","participant":"","addressingMode":"pn"},"messageTimestamp":1768904002},{"key":{"remoteJid":"553892093116@s.whatsapp.net","fromMe":false,"id":"ACA7ED8EAFFCB347402D492E8A3FFB7A","participant":"","addressingMode":"pn"},"messageTimestamp":1768904013}],"nextPreKeyId":814,"firstUnuploadedPreKeyId":814,"accountSyncCounter":1,"accountSettings":{"unarchiveChats":false},"registered":false,"account":{"details":"CJGI3qUGENKbu8sGGAYgACgA","accountSignatureKey":"tYody0QjhbzXFpECeNNqz4rDb1vC79fbndZ+W5eZN2g=","accountSignature":"G6A7GIm/h6jLz8EY0FiYyQjsw4A249UEJb6o1Mctpv7w7zz/o92dL3KJgoqS7CpgWZq+UD1waaoegpKUtOc4Dg==","deviceSignature":"+QM2VTqfLoT82ebeaEhEmzzhLxjYTfMrNNi2VdG51+KpnQ10o/4AvgXAQZgYo1WomhqhE/HPfB68+7JGuUg9hg=="},"me":{"id":"553892093116:20@s.whatsapp.net","lid":"104981969522774:20@lid","name":"Sarah"},"signalIdentities":[{"identifier":{"name":"104981969522774:20@lid","deviceId":0},"identifierKey":{"type":"Buffer","data":"BbWKHctEI4W81xaRAnjTas+Kw29bwu/X253WfluXmTdo"}}],"platform":"android","routingInfo":{"type":"Buffer","data":"CAUIDQgS"},"lastAccountSyncTimestamp":1768869337,"lastPropHash":"PWk5B","myAppStateKeyId":"AAAAAPwk"}